ez_convert/__init__.py
ez_convert/main.py
ez_convert/utils.py
ez_convert-0.1.1.dist-info/METADATA
ez_convert-0.1.1.dist-info/WHEEL
ez_convert-0.1.1.dist-info/entry_points.txt
ez_convert-0.1.1.dist-info/top_level.txt
ez_convert-0.1.1.dist-info/RECORD
