Metadata-Version: 2.1
Name: ez-convert
Version: 0.1.1
Summary: A simple command line tool to convert files from one form to another.
Home-page: https://github.com/malekinho8/ez-convert
Author: Malek Ibrahim
Author-email: shmeek8@gmail.com
Classifier: Programming Language :: Python :: 3
Classifier: License :: OSI Approved :: MIT License
Classifier: Operating System :: OS Independent
Requires-Dist: click
Requires-Dist: pyperclip
Requires-Dist: Pillow
Requires-Dist: moviepy
